super_expressive/__init__.py
super_expressive/base.py
super_expressive/main.py
super_expressive-1.0.3.dist-info/LICENSE
super_expressive-1.0.3.dist-info/METADATA
super_expressive-1.0.3.dist-info/WHEEL
super_expressive-1.0.3.dist-info/top_level.txt
super_expressive-1.0.3.dist-info/RECORD
