Metadata-Version: 2.1
Name: super-expressive
Version: 1.0.3
Summary: Python port of the JS library: https://github.com/francisrstokes/super-expressive
Author-email: Stanislav Tsaplev <stanislav.tsaplev@gmail.com>
Project-URL: homepage, https://github.com/stanislav-tsaplev/super_expressive
Project-URL: bugtracker, https://github.com/stanislav-tsaplev/super_expressive/issues
Project-URL: documentation, https://github.com/stanislav-tsaplev/super_expressive/README.md
Project-URL: repository, https://github.com/stanislav-tsaplev/super_expressive
Classifier: Programming Language :: Python :: 3
Classifier: License :: OSI Approved :: MIT License
Classifier: Operating System :: OS Independent
Requires-Python: >=3.10
License-File: LICENSE
